Workbook
Name Coffee_Type: final_sheet!$K$2:$K$1001
Name Coffee_Type_Name: final_sheet!$P$2:$P$1001
Name Country: final_sheet!$J$2:$J$1001
Name Customer_ID: final_sheet!$E$2:$E$1001
Name Customer_Name: final_sheet!$H$2:$H$1001
Name Email: final_sheet!$I$2:$I$1001
Name Order_Date: final_sheet!$B$2:$B$1001
Name Order_ID: final_sheet!$A$2:$A$1001
Name Product_ID: final_sheet!$F$2:$F$1001
Name Quantity: final_sheet!$G$2:$G$1001
Name Roast_Type: final_sheet!$L$2:$L$1001
Name Roast_Type_Name: final_sheet!$Q$2:$Q$1001
Name Sales: final_sheet!$O$2:$O$1001
Name Size: final_sheet!$M$2:$M$1001
Name Slicer_Country: #N/A
Name Slicer_Loyalty_Card: #N/A
Name Slicer_Roast_Type_Name: #N/A
Name Slicer_Size: #N/A
Name Slicer_Year: #N/A
Name Unit_Price: final_sheet!$N$2:$N$1001

Sheet orders
A1: Order ID | B1: Order Date | C1: Customer ID | D1: Product ID | E1: Quantity | F1: Customer Name | G1: Email | H1: Country | I1: Coffee Type | J1: Roast Type | K1: Size | L1: Unit Price | M1: Sales
A2: QEV-37451-860 | B2: 43713 | C2: 17670-51384-MA | D2: R-M-1 | E2: 2
A3: QEV-37451-860 | B3: 43713 | C3: 17670-51384-MA | D3: E-M-0.5 | E3: 5
A4: FAA-43335-268 | B4: 44364 | C4: 21125-22134-PX | D4: A-L-1 | E4: 1
A5: KAC-83089-793 | B5: 44392 | C5: 23806-46781-OU | D5: E-M-1 | E5: 2
A6: KAC-83089-793 | B6: 44392 | C6: 23806-46781-OU | D6: R-L-2.5 | E6: 2
A7: CVP-18956-553 | B7: 44412 | C7: 86561-91660-RB | D7: L-D-1 | E7: 3
A8: IPP-31994-879 | B8: 44582 | C8: 65223-29612-CB | D8: E-D-0.5 | E8: 3
A9: SNZ-65340-705 | B9: 44701 | C9: 21134-81676-FR | D9: L-L-0.2 | E9: 1
A10: EZT-46571-659 | B10: 43467 | C10: 03396-68805-ZC | D10: R-M-0.5 | E10: 3
A11: NWQ-70061-912 | B11: 43713 | C11: 61021-27840-ZN | D11: R-M-0.5 | E11: 1
A12: BKK-47233-845 | B12: 44263 | C12: 76239-90137-UQ | D12: A-D-1 | E12: 4
A13: VQR-01002-970 | B13: 44132 | C13: 49315-21985-BB | D13: E-L-2.5 | E13: 5
... A1001: IRV-20769-219 | B1001: 44119 | C1001: 77131-58092-GE | D1001: E-M-0.2 | E1001: 3

Sheet customers
A1: Customer ID | B1: Customer Name | C1: Email | D1: Phone Number | E1: Address Line 1 | F1: City | G1: Country | H1: Postcode | I1: Loyalty Card
A2: 17670-51384-MA | B2: Aloisia Allner | C2: aallner0@lulu.com | D2: +1 (862) 817-0124 | E2: 57999 Pepper Wood Alley | F2: Paterson | G2: United States | H2: 7505 | I2: Yes
A3: 73342-18763-UW | B3: Piotr Bote | C3: pbote1@yelp.com | D3: +353 (913) 396-4653 | E3: 2112 Ridgeway Hill | F3: Crumlin | G3: Ireland | H3: D6W | I3: No
A4: 21125-22134-PX | B4: Jami Redholes | C4: jredholes2@tmall.com | D4: +1 (210) 986-6806 | E4: 5214 Bartillon Park | F4: San Antonio | G4: United States | H4: 78205 | I4: Yes
A5: 71253-00052-RN | B5: Dene Azema | C5: dazema3@facebook.com | D5: +1 (217) 418-0714 | E5: 27 Maywood Place | F5: Springfield | G5: United States | H5: 62711 | I5: Yes
A6: 23806-46781-OU | B6: Christoffer O' Shea | D6: +353 (698) 362-9201 | E6: 38980 Manitowish Junction | F6: Cill Airne | G6: Ireland | H6: N41 | I6: No
A7: 86561-91660-RB | B7: Beryle Cottier | D7: +1 (570) 289-7473 | E7: 2651 Stoughton Place | F7: Scranton | G7: United States | H7: 18505 | I7: No
A8: 65223-29612-CB | B8: Shaylynn Lobe | C8: slobe6@nifty.com | D8: +1 (937) 954-4541 | E8: 7005 Mariners Cove Place | F8: Dayton | G8: United States | H8: 45440 | I8: Yes
A9: 21134-81676-FR | B9: Melvin Wharfe | D9: +353 (507) 574-3034 | E9: 7 Straubel Road | F9: Kill | G9: Ireland | H9: P24 | I9: Yes
A10: 03396-68805-ZC | B10: Guthrey Petracci | C10: gpetracci8@livejournal.com | D10: +1 (310) 868-1842 | E10: 949 Paget Parkway | F10: Los Angeles | G10: United States | H10: 90045 | I10: No
A11: 61021-27840-ZN | B11: Rodger Raven | C11: rraven9@ed.gov | D11: +1 (213) 263-0288 | E11: 1 Reinke Avenue | F11: Los Angeles | G11: United States | H11: 90065 | I11: No
A12: 76239-90137-UQ | B12: Ferrell Ferber | C12: fferbera@businesswire.com | D12: +1 (408) 383-5302 | E12: 68 High Crossing Court | F12: San Jose | G12: United States | H12: 95160 | I12: No
A13: 49315-21985-BB | B13: Duky Phizackerly | C13: dphizackerlyb@utexas.edu | D13: +1 (408) 533-6012 | E13: 28643 Bluejay Crossing | F13: San Jose | G13: United States | H13: 95194 | I13: Yes
A14: 34136-36674-OM | B14: Rosaleen Scholar | C14: rscholarc@nyu.edu | D14: +1 (804) 420-0420 | E14: 80915 Montana Park | F14: Richmond | G14: United States | H14: 23285 | I14: No
A15: 39396-12890-PE | B15: Terence Vanyutin | C15: tvanyutind@wix.com | E15: 331 Bunting Hill | F15: Migrate | G15: United States | H15: 41905 | I15: No
A16: 95875-73336-RG | B16: Patrice Trobe | C16: ptrobee@wunderground.com | D16: +1 (314) 240-7896 | E16: 827 Declaration Plaza | F16: Saint Louis | G16: United States | H16: 63131 | I16: Yes
A17: 25473-43727-BY | B17: Llywellyn Oscroft | C17: loscroftf@ebay.co.uk | E17: 022 Roth Place | F17: Philadelphia | G17: United States | H17: 19172 | I17: No
A18: 99643-51048-IQ | B18: Minni Alabaster | C18: malabasterg@hexun.com | D18: +1 (971) 483-6255 | E18: 3 Charing Cross Trail | F18: Portland | G18: United States | H18: 97271 | I18: No
A19: 62173-15287-CU | B19: Rhianon Broxup | C19: rbroxuph@jimdo.com | D19: +1 (713) 663-1338 | E19: 83517 Thierer Court | F19: Houston | G19: United States | H19: 77240 | I19: No
A20: 57611-05522-ST | B20: Pall Redford | C20: predfordi@ow.ly | E20: 7337 Hayes Junction | F20: Caherconlish | G20: Ireland | H20: F45 | I20: Yes
A21: 76664-37050-DT | B21: Aurea Corradino | C21: acorradinoj@harvard.edu | D21: +1 (646) 202-5965 | E21: 698 Canary Terrace | F21: New York City | G21: United States | H21: 10060 | I21: Yes
A22: 84565-53984-SX | B22: Kendal Scardefield | D22: +353 (733) 405-3302 | E22: 3 Northridge Crossing | F22: Clondalkin | G22: Ireland | H22: D24 | I22: Yes
A23: 03090-88267-BQ | B23: Avrit Davidowsky | C23: adavidowskyl@netvibes.com | D23: +1 (616) 481-9962 | E23: 9 Warrior Junction | F23: Grand Rapids | G23: United States | H23: 49560 | I23: No
A24: 37651-47492-NC | B24: Annabel Antuk | C24: aantukm@kickstarter.com | D24: +1 (941) 740-6268 | E24: 77965 Lawn Park | F24: Punta Gorda | G24: United States | H24: 33982 | I24: Yes
A25: 95399-57205-HI | B25: Iorgo Kleinert | C25: ikleinertn@timesonline.co.uk | D25: +1 (360) 352-6598 | E25: 1 Morningstar Lane | F25: Vancouver | G25: United States | H25: 98682 | I25: Yes
A26: 24010-66714-HW | B26: Chrisy Blofeld | C26: cblofeldo@amazon.co.uk | D26: +1 (303) 936-3357 | E26: 013 Talisman Terrace | F26: Englewood | G26: United States | H26: 80150 | I26: No
A27: 07591-92789-UA | B27: Culley Farris | D27: +1 (941) 267-4822 | E27: 4 Mitchell Drive | F27: Punta Gorda | G27: United States | H27: 33982 | I27: Yes
A28: 49231-44455-IC | B28: Selene Shales | C28: sshalesq@umich.edu | D28: +1 (707) 881-5004 | E28: 74 Bultman Plaza | F28: Petaluma | G28: United States | H28: 94975 | I28: Yes
A29: 50124-88608-EO | B29: Vivie Danneil | C29: vdanneilr@mtv.com | D29: +353 (751) 346-0399 | E29: 5626 Darwin Avenue | F29: Tralee | G29: Ireland | H29: V92 | I29: No
A30: 00888-74814-UZ | B30: Theresita Newbury | C30: tnewburys@usda.gov | D30: +353 (803) 587-0026 | E30: 79526 Bultman Lane | F30: Clonskeagh | G30: Ireland | H30: D04 | I30: No
A31: 14158-30713-OB | B31: Mozelle Calcutt | C31: mcalcuttt@baidu.com | D31: +353 (928) 869-1762 | E31: 4389 Russell Way | F31: Rathwire | G31: Ireland | H31: Y25 | I31: Yes
A32: 51427-89175-QJ | B32: Adrian Swaine | D32: +1 (303) 486-9517 | E32: 95 Straubel Hill | F32: Aurora | G32: United States | H32: 80044 | I32: No
A33: 52082-49024-ON | B33: Ray Leivesley | C33: rleivesleyv@canalblog.com | D33: +1 (212) 535-7791 | E33: 91 Stephen Drive | F33: Jamaica | G33: United States | H33: 11407 | I33: No
A34: 04540-43685-DV | B34: Nelly Basezzi | C34: nbasezziw@webeden.co.uk | D34: +353 (125) 815-7345 | E34: 923 Mallard Junction | F34: Bailieborough | G34: Ireland | H34: C15 | I34: Yes
A35: 39123-12846-YJ | B35: Gallard Gatheral | C35: ggatheralx@123-reg.co.uk | E35: 40 Clemons Place | F35: Grand Forks | G35: United States | H35: 58207 | I35: No
A36: 44981-99666-XB | B36: Una Welberry | C36: uwelberryy@ebay.co.uk | D36: +44 (392) 503-8132 | E36: 40915 Schlimgen Park | F36: Upton | G36: United Kingdom | H36: DN21 | I36: Yes
A37: 24825-51803-CQ | B37: Faber Eilhart | C37: feilhartz@who.int | D37: +1 (304) 510-6095 | E37: 6966 Victoria Street | F37: Charleston | G37: United States | H37: 25362 | I37: No
A38: 77634-13918-GJ | B38: Zorina Ponting | C38: zponting10@altervista.org | D38: +1 (501) 172-1476 | E38: 7118 Holmberg Court | F38: Little Rock | G38: United States | H38: 72204 | I38: No
A39: 13694-25001-LX | B39: Silvio Strase | C39: sstrase11@booking.com | D39: +1 (303) 579-8015 | E39: 5 Forest Lane | F39: Denver | G39: United States | H39: 80291 | I39: No
A40: 08523-01791-TI | B40: Dorie de la Tremoille | C40: dde12@unesco.org | D40: +1 (612) 492-5160 | E40: 0817 Dennis Street | F40: Minneapolis | G40: United States | H40: 55458 | I40: No
A41: 49860-68865-AB | B41: Hy Zanetto | E41: 469 Paget Place | F41: Tucson | G41: United States | H41: 85715 | I41: Yes
A42: 21240-83132-SP | B42: Jessica McNess | D42: +1 (504) 545-1478 | E42: 664 Erie Place | F42: New Orleans | G42: United States | H42: 70116 | I42: No
A43: 08350-81623-TF | B43: Lorenzo Yeoland | C43: lyeoland15@pbs.org | D43: +1 (860) 576-2887 | E43: 8510 Merrick Road | F43: Hartford | G43: United States | H43: 6183 | I43: Yes
A44: 73284-01385-SJ | B44: Abigail Tolworthy | C44: atolworthy16@toplist.cz | D44: +1 (801) 722-4425 | E44: 74 Shopko Way | F44: Ogden | G44: United States | H44: 84409 | I44: Yes
A45: 04152-34436-IE | B45: Maurie Bartol | D45: +1 (617) 493-7594 | E45: 7625 Starling Court | F45: Boston | G45: United States | H45: 2216 | I45: No
A46: 06631-86965-XP | B46: Olag Baudassi | C46: obaudassi18@seesaa.net | D46: +1 (585) 356-6251 | E46: 55 Dottie Court | F46: Rochester | G46: United States | H46: 14604 | I46: Yes
A47: 54619-08558-ZU | B47: Petey Kingsbury | C47: pkingsbury19@comcast.net | D47: +1 (917) 705-8224 | E47: 28 Loftsgordon Place | F47: Bronx | G47: United States | H47: 10469 | I47: No
A48: 85589-17020-CX | B48: Donna Baskeyfied | D48: +1 (205) 923-1460 | E48: 7586 Logan Avenue | F48: Birmingham | G48: United States | H48: 35205 | I48: Yes
A49: 36078-91009-WU | B49: Arda Curley | C49: acurley1b@hao123.com | D49: +1 (760) 840-3808 | E49: 45098 Scott Drive | F49: San Bernardino | G49: United States | H49: 92415 | I49: Yes
A50: 15770-27099-GX | B50: Raynor McGilvary | C50: rmcgilvary1c@tamu.edu | E50: 496 Rockefeller Court | F50: Norfolk | G50: United States | H50: 23514 | I50: No
A51: 91460-04823-BX | B51: Isis Pikett | C51: ipikett1d@xinhuanet.com | D51: +1 (202) 871-9039 | E51: 5892 Hauk Drive | F51: Washington | G51: United States | H51: 20409 | I51: No
A52: 45089-52817-WN | B52: Inger Bouldon | C52: ibouldon1e@gizmodo.com | D52: +1 (754) 391-4736 | E52: 925 Barby Circle | F52: Fort Lauderdale | G52: United States | H52: 33355 | I52: No
A53: 76447-50326-IC | B53: Karry Flanders | C53: kflanders1f@over-blog.com | D53: +353 (467) 720-7274 | E53: 88 Blue Bill Park Avenue | F53: Crumlin | G53: Ireland | H53: D6W | I53: Yes
A54: 26333-67911-OL | B54: Hartley Mattioli | C54: hmattioli1g@webmd.com | E54: 126 Valley Edge Street | F54: Kinloch | G54: United Kingdom | H54: PH43 | I54: No
A55: 40768-49176-BL | B55: Horatio Rubberts | C55: hrubberts1h@google.com.hk | D55: +1 (801) 635-8791 | E55: 459 Russell Center | F55: Provo | G55: United States | H55: 84605 | I55: No
A56: 22107-86640-SB | B56: Archambault Gillard | C56: agillard1i@issuu.com | D56: +1 (419) 663-2236 | E56: 97490 Susan Avenue | F56: Toledo | G56: United States | H56: 43666 | I56: No
A57: 09960-34242-LZ | B57: Salomo Cushworth | D57: +1 (609) 409-7044 | E57: 44 Oneill Parkway | F57: Trenton | G57: United States | H57: 8650 | I57: No
A58: 04671-85591-RT | B58: Theda Grizard | C58: tgrizard1k@odnoklassniki.ru | D58: +1 (813) 243-2150 | E58: 6 Knutson Pass | F58: Tampa | G58: United States | H58: 33686 | I58: Yes
A59: 25729-68859-UA | B59: Rozele Relton | C59: rrelton1l@stanford.edu | D59: +1 (850) 626-1181 | E59: 2484 Reindahl Court | F59: Pensacola | G59: United States | H59: 32590 | I59: No
A60: 05501-86351-NX | B60: Willa Rolling | D60: +1 (813) 759-3534 | E60: 3 Mockingbird Plaza | F60: Zephyrhills | G60: United States | H60: 33543 | I60: Yes
A61: 04521-04300-OK | B61: Stanislaus Gilroy | C61: sgilroy1n@eepurl.com | E61: 9120 Harbort Terrace | F61: Saint Paul | G61: United States | H61: 55123 | I61: Yes
A62: 58689-55264-VK | B62: Correy Cottingham | C62: ccottingham1o@wikipedia.org | D62: +1 (260) 764-1820 | E62: 394 Logan Road | F62: Fort Wayne | G62: United States | H62: 46862 | I62: No
A63: 79436-73011-MM | B63: Pammi Endacott | D63: +44 (177) 260-5076 | E63: 5841 Atwood Lane | F63: Wootton | G63: United Kingdom | H63: NN4 | I63: Yes
A64: 65552-60476-KY | B64: Nona Linklater | D64: +1 (239) 347-9766 | E64: 856 Bonner Parkway | F64: Naples | G64: United States | H64: 34114 | I64: Yes
A65: 69904-02729-YS | B65: Annadiane Dykes | C65: adykes1r@eventbrite.com | D65: +1 (312) 111-6203 | E65: 31 Northport Terrace | F65: Chicago | G65: United States | H65: 60681 | I65: No
A66: 01433-04270-AX | B66: Felecia Dodgson | D66: +1 (973) 434-8662 | E66: 48053 8th Crossing | F66: Newark | G66: United States | H66: 7104 | I66: Yes
A67: 14204-14186-LA | B67: Angelia Cockrem | C67: acockrem1t@engadget.com | D67: +1 (571) 316-8217 | E67: 1 Sherman Alley | F67: Vienna | G67: United States | H67: 22184 | I67: Yes
A68: 32948-34398-HC | B68: Belvia Umpleby | C68: bumpleby1u@soundcloud.com | D68: +1 (682) 627-0888 | E68: 710 Prairie Rose Terrace | F68: Fort Worth | G68: United States | H68: 76178 | I68: Yes
A69: 77343-52608-FF | B69: Nat Saleway | C69: nsaleway1v@dedecms.com | D69: +1 (323) 473-0294 | E69: 0780 Anthes Plaza | F69: Burbank | G69: United States | H69: 91505 | I69: No
A70: 42770-36274-QA | B70: Hayward Goulter | C70: hgoulter1w@abc.net.au | D70: +1 (423) 764-7751 | E70: 2081 Mariners Cove Drive | F70: Kingsport | G70: United States | H70: 37665 | I70: No
A71: 14103-58987-ZU | B71: Gay Rizzello | C71: grizzello1x@symantec.com | D71: +44 (247) 225-8003 | E71: 21 Schmedeman Crossing | F71: Liverpool | G71: United Kingdom | H71: L33 | I71: Yes
A72: 69958-32065-SW | B72: Shannon List | C72: slist1y@mapquest.com | D72: +1 (614) 279-9816 | E72: 7123 Algoma Center | F72: Columbus | G72: United States | H72: 43231 | I72: No
A73: 69533-84907-FA | B73: Shirlene Edmondson | C73: sedmondson1z@theguardian.com | D73: +353 (248) 428-7978 | E73: 4752 International Point | F73: Newmarket on Fergus | G73: Ireland | H73: P17 | I73: No
A74: 76005-95461-CI | B74: Aurlie McCarl | D74: +1 (504) 209-2724 | E74: 731 David Park | F74: New Orleans | G74: United States | H74: 70183 | I74: No
A75: 15395-90855-VB | B75: Alikee Carryer | D75: +1 (704) 799-5219 | E75: 247 Helena Drive | F75: Charlotte | G75: United States | H75: 28230 | I75: Yes
A76: 80640-45811-LB | B76: Jennifer Rangall | C76: jrangall22@newsvine.com | D76: +1 (781) 512-6637 | E76: 0 Grasskamp Lane | F76: Springfield | G76: United States | H76: 1114 | I76: Yes
A77: 28476-04082-GR | B77: Kipper Boorn | C77: kboorn23@ezinearticles.com | D77: +353 (359) 134-1550 | E77: 9513 Meadow Ridge Parkway | F77: Listowel | G77: Ireland | H77: V31 | I77: Yes
A78: 12018-75670-EU | B78: Melania Beadle | D78: +353 (569) 458-9673 | E78: 4418 Quincy Terrace | F78: Moycullen | G78: Ireland | H78: A41 | I78: Yes
A79: 86437-17399-FK | B79: Colene Elgey | C79: celgey25@webs.com | D79: +1 (432) 261-0702 | E79: 45 Marcy Crossing | F79: Midland | G79: United States | H79: 79705 | I79: No
A80: 62979-53167-ML | B80: Lothaire Mizzi | C80: lmizzi26@rakuten.co.jp | D80: +1 (214) 719-8530 | E80: 74 Atwood Lane | F80: Dallas | G80: United States | H80: 75323 | I80: Yes
A81: 54810-81899-HL | B81: Cletis Giacomazzo | C81: cgiacomazzo27@jigsy.com | D81: +1 (571) 703-2064 | E81: 817 Ridgeway Hill | F81: Dulles | G81: United States | H81: 20189 | I81: No
A82: 26103-41504-IB | B82: Ami Arnow | C82: aarnow28@arizona.edu | D82: +1 (650) 238-1964 | E82: 12 Oakridge Court | F82: Oakland | G82: United States | H82: 94627 | I82: Yes
A83: 76534-45229-SG | B83: Sheppard Yann | C83: syann29@senate.gov | D83: +1 (719) 803-5276 | E83: 4 Farmco Place | F83: Colorado Springs | G83: United States | H83: 80930 | I83: Yes
A84: 81744-27332-RR | B84: Bunny Naulls | C84: bnaulls2a@tiny.cc | D84: +353 (809) 128-0755 | E84: 595 Melby Avenue | F84: Adare | G84: Ireland | H84: H54 | I84: Yes
A85: 91513-75657-PH | B85: Hally Lorait | D85: +1 (716) 869-3749 | E85: 80 Jana Avenue | F85: Buffalo | G85: United States | H85: 14205 | I85: Yes
A86: 30373-66619-CB | B86: Zaccaria Sherewood | C86: zsherewood2c@apache.org | D86: +1 (209) 433-7924 | E86: 1325 Jay Terrace | F86: Fresno | G86: United States | H86: 93715 | I86: No
A87: 31582-23562-FM | B87: Jeffrey Dufaire | C87: jdufaire2d@fc2.com | E87: 8 Buell Junction | F87: Fort Worth | G87: United States | H87: 76121 | I87: No
A88: 58638-01029-CB | B88: Blancha McAmish | C88: bmcamish2e@tripadvisor.com | E88: 5484 Stephen Court | F88: Oklahoma City | G88: United States | H88: 73179 | I88: Yes
A89: 81431-12577-VD | B89: Beitris Keaveney | C89: bkeaveney2f@netlog.com | E89: 67319 Redwing Parkway | F89: Beaumont | G89: United States | H89: 77705 | I89: No
A90: 68894-91205-MP | B90: Elna Grise | C90: egrise2g@cargocollective.com | E90: 92 Becker Circle | F90: Reno | G90: United States | H90: 89519 | I90: No
A91: 87602-55754-VN | B91: Torie Gottelier | C91: tgottelier2h@vistaprint.com | D91: +1 (816) 743-8492 | E91: 426 Division Avenue | F91: Kansas City | G91: United States | H91: 64136 | I91: No
A92: 39181-35745-WH | B92: Loydie Langlais | D92: +353 (576) 222-5069 | E92: 290 Ilene Street | F92: Crumlin | G92: Ireland | H92: D6W | I92: Yes
A93: 30381-64762-NG | B93: Adham Greenhead | C93: agreenhead2j@dailymail.co.uk | D93: +1 (951) 797-0738 | E93: 0062 Spenser Place | F93: Corona | G93: United States | H93: 92878 | I93: No
A94: 17503-27693-ZH | B94: Hamish MacSherry | D94: +1 (512) 430-4374 | E94: 7 Brentwood Plaza | F94: Austin | G94: United States | H94: 78759 | I94: Yes
A95: 89442-35633-HJ | B95: Else Langcaster | C95: elangcaster2l@spotify.com | D95: +44 (547) 590-3103 | E95: 3658 Jenna Street | F95: Normanton | G95: United Kingdom | H95: LE15 | I95: Yes
A96: 13654-85265-IL | B96: Rudy Farquharson | E96: 30178 Claremont Road | F96: Charlesland | G96: Ireland | H96: A63 | I96: Yes
A97: 40946-22090-FP | B97: Norene Magauran | C97: nmagauran2n@51.la | E97: 567 Artisan Place | F97: Fresno | G97: United States | H97: 93762 | I97: No
A98: 29050-93691-TS | B98: Vicki Kirdsch | C98: vkirdsch2o@google.fr | E98: 0263 Golf Street | F98: Saint Louis | G98: United States | H98: 63150 | I98: No
A99: 64395-74865-WF | B99: Ilysa Whapple | C99: iwhapple2p@com.com | D99: +1 (559) 522-1152 | E99: 41598 Everett Drive | F99: Fresno | G99: United States | H99: 93726 | I99: No
A100: 81861-66046-SU | B100: Ruy Cancellieri | D100: +353 (338) 743-8327 | E100: 251 Welch Parkway | F100: Confey | G100: Ireland | H100: A86 | I100: No
...

Sheet products
A1: Product ID | B1: Coffee Type | C1: Roast Type | D1: Size | E1: Unit Price | F1: Price per 100g | G1: Profit
A2: A-L-0.2 | B2: Ara | C2: L | D2: 0.2 | E2: 3.885 | F2: 1.9425 | G2: 0.34965
A3: A-L-0.5 | B3: Ara | C3: L | D3: 0.5 | E3: 7.77 | F3: 1.554 | G3: 0.6993
A4: A-L-1 | B4: Ara | C4: L | D4: 1 | E4: 12.95 | F4: 1.295 | G4: 1.1655
A5: A-L-2.5 | B5: Ara | C5: L | D5: 2.5 | E5: 29.785 | F5: 1.1914 | G5: 2.68065
A6: A-M-0.2 | B6: Ara | C6: M | D6: 0.2 | E6: 3.375 | F6: 1.6875 | G6: 0.30375
A7: A-M-0.5 | B7: Ara | C7: M | D7: 0.5 | E7: 6.75 | F7: 1.35 | G7: 0.6075
A8: A-M-1 | B8: Ara | C8: M | D8: 1 | E8: 11.25 | F8: 1.125 | G8: 1.0125
A9: A-M-2.5 | B9: Ara | C9: M | D9: 2.5 | E9: 25.875 | F9: 1.035 | G9: 2.32875
A10: A-D-0.2 | B10: Ara | C10: D | D10: 0.2 | E10: 2.985 | F10: 1.4925 | G10: 0.26865
A11: A-D-0.5 | B11: Ara | C11: D | D11: 0.5 | E11: 5.97 | F11: 1.194 | G11: 0.5373
A12: A-D-1 | B12: Ara | C12: D | D12: 1 | E12: 9.95 | F12: 0.995 | G12: 0.8955
A13: A-D-2.5 | B13: Ara | C13: D | D13: 2.5 | E13: 22.885 | F13: 0.9154 | G13: 2.05965
... A49: E-D-2.5 | B49: Exc | C49: D | D49: 2.5 | E49: 27.945 | F49: 1.1178 | G49: 3.07395

Sheet final_sheet
A1: Order ID | B1: Order Date | C1: Month | D1: Year | E1: Customer ID | F1: Product ID | G1: Quantity | H1: Customer Name | I1: Email | J1: Country | K1: Coffee Type | L1: Roast Type | M1: Size | N1: Unit Price | O1: Sales | P1: Coffee Type Name | Q1: Roast Type Name | R1: Loyalty Card
A2: OJU-34452-896 | B2: 43500 | C2: =Orders[[#This Row],[Order Date]] -> 43500 | D2: =YEAR(Orders[[#This Row],[Order Date]]) -> 2019 | E2: 60799-92593-CX | F2: E-L-0.5 | G2: 1 | H2: =INDEX(customers!$A$1:$I$1001,MATCH($E2,customers!$A$1:$A$1001,),MATCH($H$1,customers!$A$1:$I$1,0)) -> Abba Pummell | I2: =IF(INDEX(customers!$A$1:$I$1001,MATCH($E2,customers!$A$1:$A$1001,0),3)=0,"",INDEX(customers!$A$1:$I$1001,MATCH($E2,customers!$A$1:$A$1001,0),3)) | J2: =_xlfn.XLOOKUP(E2,customers!$A$1:$A$1001,customers!$G$1:$G$1001) -> United States | K2: =INDEX(products!$A$1:$G$49,MATCH($F2,products!$A$1:$A$49,0),MATCH(K$1,products!$A$1:$G$1,0)) -> Exc | L2: =INDEX(products!$A$1:$G$49,MATCH($F2,products!$A$1:$A$49,0),MATCH(L$1,products!$A$1:$G$1,0)) -> L | M2: =INDEX(products!$A$1:$G$49,MATCH($F2,products!$A$1:$A$49,0),MATCH(M$1,products!$A$1:$G$1,0)) -> 0.5 | N2: =INDEX(products!$A$1:$G$49,MATCH($F2,products!$A$1:$A$49,0),MATCH(N$1,products!$A$1:$G$1,0)) -> 8.91 | O2: =N2*G2 -> 8.91 | P2: {=_xlfn.IFS(K2="Rob","Robusta",K2="Exc","Excelsa",K2="Ara","Arabica",K2="Lib","Liberica")} -> Excelsa | Q2: {=_xlfn.IFS(L2="M","Medium",L2="L","Light",L2="D","Dark")} -> Light | R2: =_xlfn.XLOOKUP(Orders[[#This Row],[Customer ID]],customers!$A$1:$A$1001,customers!$I$1:$I$1001) -> Yes
A3: NEX-63825-598 | B3: 43883 | C3: =Orders[[#This Row],[Order Date]] -> 43883 | D3: =YEAR(Orders[[#This Row],[Order Date]]) -> 2020 | E3: 72072-33025-SD | F3: R-L-0.5 | G3: 2 | H3: =INDEX(customers!$A$1:$I$1001,MATCH($E3,customers!$A$1:$A$1001,),MATCH($H$1,customers!$A$1:$I$1,0)) -> Abbe Thys | I3: =IF(INDEX(customers!$A$1:$I$1001,MATCH($E3,customers!$A$1:$A$1001,0),3)=0,"",INDEX(customers!$A$1:$I$1001,MATCH($E3,customers!$A$1:$A$1001,0),3)) -> athysfo@cdc.gov | J3: =_xlfn.XLOOKUP(E3,customers!$A$1:$A$1001,customers!$G$1:$G$1001) -> United States | K3: =INDEX(products!$A$1:$G$49,MATCH($F3,products!$A$1:$A$49,0),MATCH(K$1,products!$A$1:$G$1,0)) -> Rob | L3: =INDEX(products!$A$1:$G$49,MATCH($F3,products!$A$1:$A$49,0),MATCH(L$1,products!$A$1:$G$1,0)) -> L | M3: =INDEX(products!$A$1:$G$49,MATCH($F3,products!$A$1:$A$49,0),MATCH(M$1,products!$A$1:$G$1,0)) -> 0.5 | N3: =INDEX(products!$A$1:$G$49,MATCH($F3,products!$A$1:$A$49,0),MATCH(N$1,products!$A$1:$G$1,0)) -> 7.17 | O3: =N3*G3 -> 14.34 | P3: {=_xlfn.IFS(K3="Rob","Robusta",K3="Exc","Excelsa",K3="Ara","Arabica",K3="Lib","Liberica")} -> Robusta | Q3: {=_xlfn.IFS(L3="M","Medium",L3="L","Light",L3="D","Dark")} -> Light | R3: =_xlfn.XLOOKUP(Orders[[#This Row],[Customer ID]],customers!$A$1:$A$1001,customers!$I$1:$I$1001) -> No
A4: GPU-79113-136 | B4: 43607 | C4: =Orders[[#This Row],[Order Date]] -> 43607 | D4: =YEAR(Orders[[#This Row],[Order Date]]) -> 2019 | E4: 73284-01385-SJ | F4: R-D-0.2 | G4: 3 | H4: =INDEX(customers!$A$1:$I$1001,MATCH($E4,customers!$A$1:$A$1001,),MATCH($H$1,customers!$A$1:$I$1,0)) -> Abigail Tolworthy | I4: =IF(INDEX(customers!$A$1:$I$1001,MATCH($E4,customers!$A$1:$A$1001,0),3)=0,"",INDEX(customers!$A$1:$I$1001,MATCH($E4,customers!$A$1:$A$1001,0),3)) -> atolworthy16@toplist.cz | J4: =_xlfn.XLOOKUP(E4,customers!$A$1:$A$1001,customers!$G$1:$G$1001) -> United States | K4: =INDEX(products!$A$1:$G$49,MATCH($F4,products!$A$1:$A$49,0),MATCH(K$1,products!$A$1:$G$1,0)) -> Rob | L4: =INDEX(products!$A$1:$G$49,MATCH($F4,products!$A$1:$A$49,0),MATCH(L$1,products!$A$1:$G$1,0)) -> D | M4: =INDEX(products!$A$1:$G$49,MATCH($F4,products!$A$1:$A$49,0),MATCH(M$1,products!$A$1:$G$1,0)) -> 0.2 | N4: =INDEX(products!$A$1:$G$49,MATCH($F4,products!$A$1:$A$49,0),MATCH(N$1,products!$A$1:$G$1,0)) -> 2.685 | O4: =N4*G4 -> 8.055 | P4: {=_xlfn.IFS(K4="Rob","Robusta",K4="Exc","Excelsa",K4="Ara","Arabica",K4="Lib","Liberica")} -> Robusta | Q4: {=_xlfn.IFS(L4="M","Medium",L4="L","Light",L4="D","Dark")} -> Dark | R4: =_xlfn.XLOOKUP(Orders[[#This Row],[Customer ID]],customers!$A$1:$A$1001,customers!$I$1:$I$1001) -> Yes
A5: PPP-78935-365 | B5: 44238 | C5: =Orders[[#This Row],[Order Date]] -> 44238 | D5: =YEAR(Orders[[#This Row],[Order Date]]) -> 2021 | E5: 91074-60023-IP | F5: E-D-1 | G5: 4 | H5: =INDEX(customers!$A$1:$I$1001,MATCH($E5,customers!$A$1:$A$1001,),MATCH($H$1,customers!$A$1:$I$1,0)) -> Abraham Coleman | I5: =IF(INDEX(customers!$A$1:$I$1001,MATCH($E5,customers!$A$1:$A$1001,0),3)=0,"",INDEX(customers!$A$1:$I$1001,MATCH($E5,customers!$A$1:$A$1001,0),3)) | J5: =_xlfn.XLOOKUP(E5,customers!$A$1:$A$1001,customers!$G$1:$G$1001) -> United States | K5: =INDEX(products!$A$1:$G$49,MATCH($F5,products!$A$1:$A$49,0),MATCH(K$1,products!$A$1:$G$1,0)) -> Exc | L5: =INDEX(products!$A$1:$G$49,MATCH($F5,products!$A$1:$A$49,0),MATCH(L$1,products!$A$1:$G$1,0)) -> D | M5: =INDEX(products!$A$1:$G$49,MATCH($F5,products!$A$1:$A$49,0),MATCH(M$1,products!$A$1:$G$1,0)) -> 1 | N5: =INDEX(products!$A$1:$G$49,MATCH($F5,products!$A$1:$A$49,0),MATCH(N$1,products!$A$1:$G$1,0)) -> 12.15 | O5: =N5*G5 -> 48.6 | P5: {=_xlfn.IFS(K5="Rob","Robusta",K5="Exc","Excelsa",K5="Ara","Arabica",K5="Lib","Liberica")} -> Excelsa | Q5: {=_xlfn.IFS(L5="M","Medium",L5="L","Light",L5="D","Dark")} -> Dark | R5: =_xlfn.XLOOKUP(Orders[[#This Row],[Customer ID]],customers!$A$1:$A$1001,customers!$I$1:$I$1001) -> No
A6: EOI-02511-919 | B6: 43910 | C6: =Orders[[#This Row],[Order Date]] -> 43910 | D6: =YEAR(Orders[[#This Row],[Order Date]]) -> 2020 | E6: 66776-88682-RG | F6: E-L-0.2 | G6: 5 | H6: =INDEX(customers!$A$1:$I$1001,MATCH($E6,customers!$A$1:$A$1001,),MATCH($H$1,customers!$A$1:$I$1,0)) -> Abrahan Mussen | I6: =IF(INDEX(customers!$A$1:$I$1001,MATCH($E6,customers!$A$1:$A$1001,0),3)=0,"",INDEX(customers!$A$1:$I$1001,MATCH($E6,customers!$A$1:$A$1001,0),3)) -> amussen50@51.la | J6: =_xlfn.XLOOKUP(E6,customers!$A$1:$A$1001,customers!$G$1:$G$1001) -> United States | K6: =INDEX(products!$A$1:$G$49,MATCH($F6,products!$A$1:$A$49,0),MATCH(K$1,products!$A$1:$G$1,0)) -> Exc | L6: =INDEX(products!$A$1:$G$49,MATCH($F6,products!$A$1:$A$49,0),MATCH(L$1,products!$A$1:$G$1,0)) -> L | M6: =INDEX(products!$A$1:$G$49,MATCH($F6,products!$A$1:$A$49,0),MATCH(M$1,products!$A$1:$G$1,0)) -> 0.2 | N6: =INDEX(products!$A$1:$G$49,MATCH($F6,products!$A$1:$A$49,0),MATCH(N$1,products!$A$1:$G$1,0)) -> 4.455 | O6: =N6*G6 -> 22.275 | P6: {=_xlfn.IFS(K6="Rob","Robusta",K6="Exc","Excelsa",K6="Ara","Arabica",K6="Lib","Liberica")} -> Excelsa | Q6: {=_xlfn.IFS(L6="M","Medium",L6="L","Light",L6="D","Dark")} -> Light | R6: =_xlfn.XLOOKUP(Orders[[#This Row],[Customer ID]],customers!$A$1:$A$1001,customers!$I$1:$I$1001) -> No
A7: EOI-02511-919 | B7: 43910 | C7: =Orders[[#This Row],[Order Date]] -> 43910 | D7: =YEAR(Orders[[#This Row],[Order Date]]) -> 2020 | E7: 66776-88682-RG | F7: A-D-0.5 | G7: 5 | H7: =INDEX(customers!$A$1:$I$1001,MATCH($E7,customers!$A$1:$A$1001,),MATCH($H$1,customers!$A$1:$I$1,0)) -> Abrahan Mussen | I7: =IF(INDEX(customers!$A$1:$I$1001,MATCH($E7,customers!$A$1:$A$1001,0),3)=0,"",INDEX(customers!$A$1:$I$1001,MATCH($E7,customers!$A$1:$A$1001,0),3)) -> amussen50@51.la | J7: =_xlfn.XLOOKUP(E7,customers!$A$1:$A$1001,customers!$G$1:$G$1001) -> United States | K7: =INDEX(products!$A$1:$G$49,MATCH($F7,products!$A$1:$A$49,0),MATCH(K$1,products!$A$1:$G$1,0)) -> Ara | L7: =INDEX(products!$A$1:$G$49,MATCH($F7,products!$A$1:$A$49,0),MATCH(L$1,products!$A$1:$G$1,0)) -> D | M7: =INDEX(products!$A$1:$G$49,MATCH($F7,products!$A$1:$A$49,0),MATCH(M$1,products!$A$1:$G$1,0)) -> 0.5 | N7: =INDEX(products!$A$1:$G$49,MATCH($F7,products!$A$1:$A$49,0),MATCH(N$1,products!$A$1:$G$1,0)) -> 5.97 | O7: =N7*G7 -> 29.85 | P7: {=_xlfn.IFS(K7="Rob","Robusta",K7="Exc","Excelsa",K7="Ara","Arabica",K7="Lib","Liberica")} -> Arabica | Q7: {=_xlfn.IFS(L7="M","Medium",L7="L","Light",L7="D","Dark")} -> Dark | R7: =_xlfn.XLOOKUP(Orders[[#This Row],[Customer ID]],customers!$A$1:$A$1001,customers!$I$1:$I$1001) -> No
A8: GNL-98714-885 | B8: 43897 | C8: =Orders[[#This Row],[Order Date]] -> 43897 | D8: =YEAR(Orders[[#This Row],[Order Date]]) -> 2020 | E8: 83731-53280-YC | F8: R-M-1 | G8: 3 | H8: =INDEX(customers!$A$1:$I$1001,MATCH($E8,customers!$A$1:$A$1001,),MATCH($H$1,customers!$A$1:$I$1,0)) -> Adele McFayden | I8: =IF(INDEX(customers!$A$1:$I$1001,MATCH($E8,customers!$A$1:$A$1001,0),3)=0,"",INDEX(customers!$A$1:$I$1001,MATCH($E8,customers!$A$1:$A$1001,0),3)) | J8: =_xlfn.XLOOKUP(E8,customers!$A$1:$A$1001,customers!$G$1:$G$1001) -> United Kingdom | K8: =INDEX(products!$A$1:$G$49,MATCH($F8,products!$A$1:$A$49,0),MATCH(K$1,products!$A$1:$G$1,0)) -> Rob | L8: =INDEX(products!$A$1:$G$49,MATCH($F8,products!$A$1:$A$49,0),MATCH(L$1,products!$A$1:$G$1,0)) -> M | M8: =INDEX(products!$A$1:$G$49,MATCH($F8,products!$A$1:$A$49,0),MATCH(M$1,products!$A$1:$G$1,0)) -> 1 | N8: =INDEX(products!$A$1:$G$49,MATCH($F8,products!$A$1:$A$49,0),MATCH(N$1,products!$A$1:$G$1,0)) -> 9.95 | O8: =N8*G8 -> 29.85 | P8: {=_xlfn.IFS(K8="Rob","Robusta",K8="Exc","Excelsa",K8="Ara","Arabica",K8="Lib","Liberica")} -> Robusta | Q8: {=_xlfn.IFS(L8="M","Medium",L8="L","Light",L8="D","Dark")} -> Medium | R8: =_xlfn.XLOOKUP(Orders[[#This Row],[Customer ID]],customers!$A$1:$A$1001,customers!$I$1:$I$1001) -> Yes
A9: VUC-72395-865 | B9: 44476 | C9: =Orders[[#This Row],[Order Date]] -> 44476 | D9: =YEAR(Orders[[#This Row],[Order Date]]) -> 2021 | E9: 13321-57602-GK | F9: A-D-0.5 | G9: 6 | H9: =INDEX(customers!$A$1:$I$1001,MATCH($E9,customers!$A$1:$A$1001,),MATCH($H$1,customers!$A$1:$I$1,0)) -> Adelheid Gladhill | I9: =IF(INDEX(customers!$A$1:$I$1001,MATCH($E9,customers!$A$1:$A$1001,0),3)=0,"",INDEX(customers!$A$1:$I$1001,MATCH($E9,customers!$A$1:$A$1001,0),3)) -> agladhillng@stanford.edu | J9: =_xlfn.XLOOKUP(E9,customers!$A$1:$A$1001,customers!$G$1:$G$1001) -> United States | K9: =INDEX(products!$A$1:$G$49,MATCH($F9,products!$A$1:$A$49,0),MATCH(K$1,products!$A$1:$G$1,0)) -> Ara | L9: =INDEX(products!$A$1:$G$49,MATCH($F9,products!$A$1:$A$49,0),MATCH(L$1,products!$A$1:$G$1,0)) -> D | M9: =INDEX(products!$A$1:$G$49,MATCH($F9,products!$A$1:$A$49,0),MATCH(M$1,products!$A$1:$G$1,0)) -> 0.5 | N9: =INDEX(products!$A$1:$G$49,MATCH($F9,products!$A$1:$A$49,0),MATCH(N$1,products!$A$1:$G$1,0)) -> 5.97 | O9: =N9*G9 -> 35.82 | P9: {=_xlfn.IFS(K9="Rob","Robusta",K9="Exc","Excelsa",K9="Ara","Arabica",K9="Lib","Liberica")} -> Arabica | Q9: {=_xlfn.IFS(L9="M","Medium",L9="L","Light",L9="D","Dark")} -> Dark | R9: =_xlfn.XLOOKUP(Orders[[#This Row],[Customer ID]],customers!$A$1:$A$1001,customers!$I$1:$I$1001) -> Yes
A10: CYH-53243-218 | B10: 44183 | C10: =Orders[[#This Row],[Order Date]] -> 44183 | D10: =YEAR(Orders[[#This Row],[Order Date]]) -> 2020 | E10: 88167-57964-PH | F10: R-M-0.5 | G10: 3 | H10: =INDEX(customers!$A$1:$I$1001,MATCH($E10,customers!$A$1:$A$1001,),MATCH($H$1,customers!$A$1:$I$1,0)) -> Adelice Isabell | I10: =IF(INDEX(customers!$A$1:$I$1001,MATCH($E10,customers!$A$1:$A$1001,0),3)=0,"",INDEX(customers!$A$1:$I$1001,MATCH($E10,customers!$A$1:$A$1001,0),3)) | J10: =_xlfn.XLOOKUP(E10,customers!$A$1:$A$1001,customers!$G$1:$G$1001) -> United States | K10: =INDEX(products!$A$1:$G$49,MATCH($F10,products!$A$1:$A$49,0),MATCH(K$1,products!$A$1:$G$1,0)) -> Rob | L10: =INDEX(products!$A$1:$G$49,MATCH($F10,products!$A$1:$A$49,0),MATCH(L$1,products!$A$1:$G$1,0)) -> M | M10: =INDEX(products!$A$1:$G$49,MATCH($F10,products!$A$1:$A$49,0),MATCH(M$1,products!$A$1:$G$1,0)) -> 0.5 | N10: =INDEX(products!$A$1:$G$49,MATCH($F10,products!$A$1:$A$49,0),MATCH(N$1,products!$A$1:$G$1,0)) -> 5.97 | O10: =N10*G10 -> 17.91 | P10: {=_xlfn.IFS(K10="Rob","Robusta",K10="Exc","Excelsa",K10="Ara","Arabica",K10="Lib","Liberica")} -> Robusta | Q10: {=_xlfn.IFS(L10="M","Medium",L10="L","Light",L10="D","Dark")} -> Medium | R10: =_xlfn.XLOOKUP(Orders[[#This Row],[Customer ID]],customers!$A$1:$A$1001,customers!$I$1:$I$1001) -> No
A11: ROV-87448-086 | B11: 44137 | C11: =Orders[[#This Row],[Order Date]] -> 44137 | D11: =YEAR(Orders[[#This Row],[Order Date]]) -> 2020 | E11: 30381-64762-NG | F11: A-M-2.5 | G11: 4 | H11: =INDEX(customers!$A$1:$I$1001,MATCH($E11,customers!$A$1:$A$1001,),MATCH($H$1,customers!$A$1:$I$1,0)) -> Adham Greenhead | I11: =IF(INDEX(customers!$A$1:$I$1001,MATCH($E11,customers!$A$1:$A$1001,0),3)=0,"",INDEX(customers!$A$1:$I$1001,MATCH($E11,customers!$A$1:$A$1001,0),3)) -> agreenhead2j@dailymail.co.uk | J11: =_xlfn.XLOOKUP(E11,customers!$A$1:$A$1001,customers!$G$1:$G$1001) -> United States | K11: =INDEX(products!$A$1:$G$49,MATCH($F11,products!$A$1:$A$49,0),MATCH(K$1,products!$A$1:$G$1,0)) -> Ara | L11: =INDEX(products!$A$1:$G$49,MATCH($F11,products!$A$1:$A$49,0),MATCH(L$1,products!$A$1:$G$1,0)) -> M | M11: =INDEX(products!$A$1:$G$49,MATCH($F11,products!$A$1:$A$49,0),MATCH(M$1,products!$A$1:$G$1,0)) -> 2.5 | N11: =INDEX(products!$A$1:$G$49,MATCH($F11,products!$A$1:$A$49,0),MATCH(N$1,products!$A$1:$G$1,0)) -> 25.875 | O11: =N11*G11 -> 103.5 | P11: {=_xlfn.IFS(K11="Rob","Robusta",K11="Exc","Excelsa",K11="Ara","Arabica",K11="Lib","Liberica")} -> Arabica | Q11: {=_xlfn.IFS(L11="M","Medium",L11="L","Light",L11="D","Dark")} -> Medium | R11: =_xlfn.XLOOKUP(Orders[[#This Row],[Customer ID]],customers!$A$1:$A$1001,customers!$I$1:$I$1001) -> No
A12: TJE-91516-344 | B12: 43730 | C12: =Orders[[#This Row],[Order Date]] -> 43730 | D12: =YEAR(Orders[[#This Row],[Order Date]]) -> 2019 | E12: 49894-06550-OQ | F12: E-M-1 | G12: 2 | H12: =INDEX(customers!$A$1:$I$1001,MATCH($E12,customers!$A$1:$A$1001,),MATCH($H$1,customers!$A$1:$I$1,0)) -> Adolphe Treherne | I12: =IF(INDEX(customers!$A$1:$I$1001,MATCH($E12,customers!$A$1:$A$1001,0),3)=0,"",INDEX(customers!$A$1:$I$1001,MATCH($E12,customers!$A$1:$A$1001,0),3)) -> atrehernecv@state.tx.us | J12: =_xlfn.XLOOKUP(E12,customers!$A$1:$A$1001,customers!$G$1:$G$1001) -> Ireland | K12: =INDEX(products!$A$1:$G$49,MATCH($F12,products!$A$1:$A$49,0),MATCH(K$1,products!$A$1:$G$1,0)) -> Exc | L12: =INDEX(products!$A$1:$G$49,MATCH($F12,products!$A$1:$A$49,0),MATCH(L$1,products!$A$1:$G$1,0)) -> M | M12: =INDEX(products!$A$1:$G$49,MATCH($F12,products!$A$1:$A$49,0),MATCH(M$1,products!$A$1:$G$1,0)) -> 1 | N12: =INDEX(products!$A$1:$G$49,MATCH($F12,products!$A$1:$A$49,0),MATCH(N$1,products!$A$1:$G$1,0)) -> 13.75 | O12: =N12*G12 -> 27.5 | P12: {=_xlfn.IFS(K12="Rob","Robusta",K12="Exc","Excelsa",K12="Ara","Arabica",K12="Lib","Liberica")} -> Excelsa | Q12: {=_xlfn.IFS(L12="M","Medium",L12="L","Light",L12="D","Dark")} -> Medium | R12: =_xlfn.XLOOKUP(Orders[[#This Row],[Customer ID]],customers!$A$1:$A$1001,customers!$I$1:$I$1001) -> No
A13: HHF-36647-854 | B13: 44505 | C13: =Orders[[#This Row],[Order Date]] -> 44505 | D13: =YEAR(Orders[[#This Row],[Order Date]]) -> 2021 | E13: 39011-18412-GR | F13: A-D-2.5 | G13: 6 | H13: =INDEX(customers!$A$1:$I$1001,MATCH($E13,customers!$A$1:$A$1001,),MATCH($H$1,customers!$A$1:$I$1,0)) -> Adora Roubert | I13: =IF(INDEX(customers!$A$1:$I$1001,MATCH($E13,customers!$A$1:$A$1001,0),3)=0,"",INDEX(customers!$A$1:$I$1001,MATCH($E13,customers!$A$1:$A$1001,0),3)) -> aroubertn0@tmall.com | J13: =_xlfn.XLOOKUP(E13,customers!$A$1:$A$1001,customers!$G$1:$G$1001) -> United States | K13: =INDEX(products!$A$1:$G$49,MATCH($F13,products!$A$1:$A$49,0),MATCH(K$1,products!$A$1:$G$1,0)) -> Ara | L13: =INDEX(products!$A$1:$G$49,MATCH($F13,products!$A$1:$A$49,0),MATCH(L$1,products!$A$1:$G$1,0)) -> D | M13: =INDEX(products!$A$1:$G$49,MATCH($F13,products!$A$1:$A$49,0),MATCH(M$1,products!$A$1:$G$1,0)) -> 2.5 | N13: =INDEX(products!$A$1:$G$49,MATCH($F13,products!$A$1:$A$49,0),MATCH(N$1,products!$A$1:$G$1,0)) -> 22.885 | O13: =N13*G13 -> 137.31 | P13: {=_xlfn.IFS(K13="Rob","Robusta",K13="Exc","Excelsa",K13="Ara","Arabica",K13="Lib","Liberica")} -> Arabica | Q13: {=_xlfn.IFS(L13="M","Medium",L13="L","Light",L13="D","Dark")} -> Dark | R13: =_xlfn.XLOOKUP(Orders[[#This Row],[Customer ID]],customers!$A$1:$A$1001,customers!$I$1:$I$1001) -> Yes
... A1001: QUQ-90580-772 | B1001: 44233 | C1001: =Orders[[#This Row],[Order Date]] -> 44233 | D1001: =YEAR(Orders[[#This Row],[Order Date]]) -> 2021 | E1001: 77634-13918-GJ | F1001: L-M-0.2 | G1001: 2 | H1001: =INDEX(customers!$A$1:$I$1001,MATCH($E1001,customers!$A$1:$A$1001,),MATCH($H$1,customers!$A$1:$I$1,0)) -> Zorina Ponting | I1001: =IF(INDEX(customers!$A$1:$I$1001,MATCH($E1001,customers!$A$1:$A$1001,0),3)=0,"",INDEX(customers!$A$1:$I$1001,MATCH($E1001,customers!$A$1:$A$1001,0),3)) -> zponting10@altervista.org | J1001: =_xlfn.XLOOKUP(E1001,customers!$A$1:$A$1001,customers!$G$1:$G$1001) -> United States | K1001: =INDEX(products!$A$1:$G$49,MATCH($F1001,products!$A$1:$A$49,0),MATCH(K$1,products!$A$1:$G$1,0)) -> Lib | L1001: =INDEX(products!$A$1:$G$49,MATCH($F1001,products!$A$1:$A$49,0),MATCH(L$1,products!$A$1:$G$1,0)) -> M | M1001: =INDEX(products!$A$1:$G$49,MATCH($F1001,products!$A$1:$A$49,0),MATCH(M$1,products!$A$1:$G$1,0)) -> 0.2 | N1001: =INDEX(products!$A$1:$G$49,MATCH($F1001,products!$A$1:$A$49,0),MATCH(N$1,products!$A$1:$G$1,0)) -> 4.365 | O1001: =N1001*G1001 -> 8.73 | P1001: {=_xlfn.IFS(K1001="Rob","Robusta",K1001="Exc","Excelsa",K1001="Ara","Arabica",K1001="Lib","Liberica")} -> Liberica | Q1001: {=_xlfn.IFS(L1001="M","Medium",L1001="L","Light",L1001="D","Dark")} -> Medium | R1001: =_xlfn.XLOOKUP(Orders[[#This Row],[Customer ID]],customers!$A$1:$A$1001,customers!$I$1:$I$1001) -> No

Sheet total sales
A1: Year and month wise sales | H1: Country wise sales
A3: Sum of Sales | C3: Coffee Type Name | H3: Country | I3: Sum of Sales
A4: Years (Month) | B4: Months (Month) | C4: Arabica | D4: Excelsa | E4: Liberica | F4: Robusta | G4: Grand Total | H4: United Kingdom | I4: 195.49
A5: 2019 | B5: Jan | C5: 77.7 | D5: 53.46 | E5: 50.72 | F5: 21.51 | G5: 203.39 | H5: Ireland | I5: 578.845
B6: Feb | C6: 67.34 | F6: 71.7 | G6: 139.04 | H6: United States | I6: 2387.385
B7: Mar | C7: 59.57 | E7: 85.59 | F7: 28.68 | G7: 173.84
B8: Apr | C8: 64.75 | D8: 181.17 | E8: 210.805 | F8: 21.51 | G8: 478.235
B9: May | C9: 29.785 | G9: 29.785 | H9: Customer wise sales
B10: Jun | D10: 341.55 | F10: 17.925 | G10: 359.475
B11: Jul | C11: 89.355 | D11: 204.93 | E11: 171.18 | G11: 465.465 | H11: Customer Name | I11: Sum of Sales
B12: Aug | C12: 213.675 | E12: 15.85 | G12: 229.525 | H12: Redd Simao | I12: 178.71
B13: Sep | C13: 178.71 | E13: 91.93 | G13: 270.64 | H13: Samuele Ales0 | I13: 182.275
B14: Oct | C14: 103.6 | D14: 86.13 | F14: 164.91 | G14: 354.64 | H14: Daniel Heinonen | I14: 204.93
B15: Nov | E15: 187.03 | F15: 7.17 | G15: 194.2 | H15: Nanny Lush | I15: 204.93
B16: Dec | D16: 204.93 | F16: 58.555 | G16: 263.485 | H16: Shelli Keynd | I16: 204.93
A17: 2019 Total | C17: 884.485 | D17: 1072.17 | E17: 813.105 | F17: 391.96 | G17: 3161.72
A18: Grand Total | C18: 884.485 | D18: 1072.17 | E18: 813.105 | F18: 391.96 | G18: 3161.72

Sheet extra
A1: Year and month and coffee type wise order count | J1: Country and coffee type wise order count | Q1: Coffee Type Distribution (Highest Value)
A3: Count of Order ID | E3: Coffee Type Name | J3: Count of Order ID | K3: Coffee Type Name | Q3: Coffee Type Name | R3: Count of Order ID
A4: Year | B4: Years (Month) | C4: Months (Month) | D4: Month | E4: Arabica | F4: Excelsa | G4: Liberica | H4: Robusta | J4: Country | K4: Arabica | L4: Excelsa | M4: Liberica | N4: Robusta | Q4: Arabica | R4: 0.26
A5: 2019 | B5: 2019 | C5: Jan | E5: 3 | F5: 7 | G5: 5 | H5: 5 | J5: Ireland | K5: 41 | L5: 35 | M5: 39 | N5: 38 | Q5: Excelsa | R5: 0.2
C6: Feb | E6: 7 | F6: 4 | G6: 7 | H6: 5 | J6: United Kingdom | K6: 7 | L6: 23 | M6: 21 | N6: 22 | Q6: Liberica | R6: 0.3
C7: Mar | E7: 4 | F7: 7 | G7: 6 | H7: 6 | J7: United States | K7: 216 | L7: 189 | M7: 188 | N7: 181 | Q7: Robusta | R7: 0.24
C8: Apr | E8: 5 | F8: 8 | G8: 10 | H8: 6
C9: May | E9: 2 | F9: 3 | G9: 4 | H9: 4 | J9: Year and country wise order count
C10: Jun | E10: 2 | F10: 8 | G10: 4 | H10: 9
C11: Jul | E11: 8 | F11: 6 | G11: 4 | H11: 4 | J11: Count of Order ID | K11: Country | Q11: Roast Level Popularity
C12: Aug | E12: 7 | F12: 2 | G12: 3 | H12: 5 | J12: Year | K12: Ireland | L12: United Kingdom | M12: United States
C13: Sep | E13: 1 | F13: 4 | G13: 8 | H13: 11 | J13: 2019 | K13: 36 | L13: 28 | M13: 195 | Q13: Roast Type Name | R13: Count of Order ID
C14: Oct | E14: 9 | F14: 5 | G14: 4 | H14: 7 | J14: 2020 | K14: 33 | L14: 22 | M14: 208 | Q14: Light | R14: 1
C15: Nov | E15: 5 | F15: 1 | G15: 7 | H15: 4 | J15: 2021 | K15: 53 | L15: 17 | M15: 242
C16: Dec | E16: 6 | F16: 5 | G16: 6 | H16: 6 | J16: 2022 | K16: 31 | L16: 6 | M16: 129
B17: 2019 Total | E17: 59 | F17: 60 | G17: 68 | H17: 72
A18: 2019 Total | E18: 59 | F18: 60 | G18: 68 | H18: 72
A19: 2020 | B19: 2020 | C19: Jan | E19: 3 | F19: 3 | G19: 8 | H19: 6
C20: Feb | E20: 11 | F20: 9 | G20: 5 | H20: 9
C21: Mar | E21: 5 | F21: 8 | G21: 5 | H21: 5 | J21: Sum of Sales | L21: Count of Order ID
C22: Apr | E22: 1 | F22: 5 | G22: 4 | H22: 5 | J22: 3161.72 | L22: 50 | Q22: Loyalty Card | R22: Count of Loyalty Card
C23: May | E23: 7 | F23: 6 | G23: 3 | H23: 3 | J23: =GETPIVOTDATA("Sales",$J$21) -> 3161.72 | L23: =GETPIVOTDATA("Order ID",$L$21) -> 50 | N23: Average Order Size = Total Quantity Sold ÷ Total Orders | Q23: No | R23: 521
C24: Jun | E24: 7 | F24: 6 | G24: 6 | H24: 3 | K24: =GETPIVOTDATA("Sales",$J$21)/GETPIVOTDATA("Order ID",$L$21) -> 63.2344 | N24: =GETPIVOTDATA("Quantity",$L$26)/GETPIVOTDATA("Order ID",$L$21) -> 3.7 | Q24: Yes | R24: 479
C25: Jul | E25: 10 | F25: 5 | G25: 5 | H25: 9
C26: Aug | E26: 1 | F26: 3 | G26: 3 | H26: 5 | J26: Count of Customer ID | L26: Sum of Quantity
C27: Sep | E27: 4 | F27: 3 | G27: 5 | H27: 7 | J27: 50 | L27: 185
C28: Oct | E28: 9 | F28: 9 | G28: 9 | H28: 3 | J28: =GETPIVOTDATA("Customer ID",$J$26) -> 50
C29: Nov | E29: 6 | F29: 3 | G29: 5 | H29: 3
C30: Dec | E30: 6 | F30: 11 | G30: 3 | H30: 3 | Q30: Package Size Preferences
B31: 2020 Total | E31: 70 | F31: 71 | G31: 61 | H31: 61
A32: 2020 Total | E32: 70 | F32: 71 | G32: 61 | H32: 61
A33: 2021 | B33: 2021 | C33: Jan | E33: 8 | F33: 4 | G33: 9 | H33: 5 | J33: Year | K33: Sum of Sales | Q33: Size | R33: Count of Order ID
C34: Feb | E34: 6 | F34: 6 | G34: 7 | H34: 4 | J34: 2019 | K34: 12187.165 | Q34: 0.2 | R34: 249
C35: Mar | E35: 8 | F35: 11 | G35: 6 | H35: 10 | J35: 2020 | K35: 12117.545 | Q35: 0.5 | R35: 268
C36: Apr | E36: 6 | F36: 5 | G36: 6 | H36: 2 | J36: 2021 | K36: 13766.11 | L36: =GETPIVOTDATA("Sales",$J$33,"Year",2021)-GETPIVOTDATA("Sales",$J$33,"Year",2019) -> 1578.945 | M36: =L36/GETPIVOTDATA("Sales",$J$33,"Year",2019) -> 0.12955802 | Q36: 1 | R36: 236
C37: May | E37: 6 | F37: 4 | G37: 6 | H37: 8 | J37: 2022 | K37: 7063.435 | Q37: 2.5 | R37: 247
C38: Jun | E38: 8 | F38: 5 | G38: 3 | H38: 4
C39: Jul | E39: 5 | F39: 9 | G39: 3 | H39: 4
C40: Aug | E40: 8 | F40: 7 | G40: 3 | H40: 7
C41: Sep | E41: 14 | F41: 6 | G41: 6 | H41: 4 | Q41: Customer geopgraphic dist
C42: Oct | E42: 8 | F42: 5 | G42: 10 | H42: 7 | Q42: Country | R42: Count of Customer ID
C43: Nov | E43: 6 | F43: 11 | G43: 12 | H43: 5 | Q43: Ireland | R43: 0.14
C44: Dec | E44: 8 | F44: 5 | G44: 9 | H44: 3 | Q44: United Kingdom | R44: 0.16
B45: 2021 Total | E45: 91 | F45: 78 | G45: 80 | H45: 63 | Q45: United States | R45: 0.7
A46: 2021 Total | E46: 91 | F46: 78 | G46: 80 | H46: 63
A47: 2022 | B47: 2022 | C47: Jan | E47: 5 | F47: 6 | G47: 9 | H47: 5
C48: Feb | E48: 5 | F48: 4 | G48: 4 | H48: 2
C49: Mar | E49: 6 | F49: 4 | G49: 8 | H49: 10
C50: Apr | E50: 8 | F50: 6 | G50: 4 | H50: 5
C51: May | E51: 5 | F51: 5 | G51: 6 | H51: 7
C52: Jun | E52: 6 | F52: 7 | G52: 3 | H52: 7
C53: Jul | E53: 5 | F53: 5 | G53: 4 | H53: 5
C54: Aug | E54: 4 | F54: 1 | G54: 1 | H54: 4
B55: 2022 Total | E55: 44 | F55: 38 | G55: 39 | H55: 45
A56: 2022 Total | E56: 44 | F56: 38 | G56: 39 | H56: 45

Sheet Dashboard 
B7: Total Sales | G7: Total Orders | L7: Average Order Value $ | Q7: Total Customers | V7: Average Order Size
